loqed/__init__.py
loqed/__main__.py
loqed/lock.py
pyloqed-1.1.0.dist-info/LICENSE
pyloqed-1.1.0.dist-info/METADATA
pyloqed-1.1.0.dist-info/WHEEL
pyloqed-1.1.0.dist-info/top_level.txt
pyloqed-1.1.0.dist-info/RECORD
